stepping/__init__.py
stepping/graph.py
stepping/profile.py
stepping/run.py
stepping/steppingpack.py
stepping/store.py
stepping/types.py
stepping/datatypes/_btree.py
stepping/datatypes/default_dict.py
stepping/datatypes/sorted_set.py
stepping/operators/group.py
stepping/operators/lifted.py
stepping/operators/linear.py
stepping/operators/transform.py
stepping/operators/builder/__init__.py
stepping/operators/builder/ast.py
stepping/operators/builder/common.py
stepping/operators/builder/compile.py
stepping/operators/builder/traverse.py
stepping/zset/functions.py
stepping/zset/python.py
stepping/zset/sql/generic.py
stepping/zset/sql/postgres.py
stepping/zset/sql/sqlite.py
stepping-0.0.3.dist-info/METADATA
stepping-0.0.3.dist-info/WHEEL
stepping-0.0.3.dist-info/top_level.txt
stepping-0.0.3.dist-info/RECORD
