Metadata-Version: 2.1
Name: stepping
Version: 0.0.3
Summary: Incremental View Maintenance for Python backends
Author-email: Oliver Russell <ojhrussell@gmail.com>
Maintainer-email: Oliver Russell <ojhrussell@gmail.com>
Project-URL: homepage, https://stepping.site
Project-URL: documentation, https://stepping.site
Project-URL: repository, https://github.com/leontrolski/stepping.git
Keywords: IVM,postgres,sqlite
Classifier: Programming Language :: Python
Requires-Python: >=3.11
Requires-Dist: immutables >=0.19
Requires-Dist: ormsgpack >=1.3.0
Requires-Dist: psycopg >=3.1.8
Requires-Dist: psycopg-binary >=3.1.8
Requires-Dist: psycopg-pool >=3.1.7
Requires-Dist: tabulate >=0.9.0
Provides-Extra: dev
Requires-Dist: testing.postgresql >=1.3.0 ; extra == 'dev'
Requires-Dist: pytest >=7.2.2 ; extra == 'dev'
Requires-Dist: autoflake >=2.0.2 ; extra == 'dev'
Requires-Dist: black >=23.1.0 ; extra == 'dev'
Requires-Dist: icdiff >=2.0.6 ; extra == 'dev'
Requires-Dist: isort >=5.12.0 ; extra == 'dev'
Requires-Dist: mypy >=1.4.1 ; extra == 'dev'
Requires-Dist: prettyprinter >=0.18.0 ; extra == 'dev'
Requires-Dist: pydot >=1.4.2 ; extra == 'dev'
Requires-Dist: snakeviz >=2.1.1 ; extra == 'dev'
